modi_plus/__init__.py
modi_plus/__main__.py
modi_plus/_exe_thread.py
modi_plus/about.py
modi_plus/modi_plus.py
modi_plus/assets/version.txt
modi_plus/assets/firmware/esp32/bootloader.bin
modi_plus/assets/firmware/esp32/esp32.bin
modi_plus/assets/firmware/esp32/modi_ota_factory.bin
modi_plus/assets/firmware/esp32/ota_data_initial.bin
modi_plus/assets/firmware/esp32/partitions.bin
modi_plus/assets/firmware/modules/battery.bin
modi_plus/assets/firmware/modules/button.bin
modi_plus/assets/firmware/modules/dial.bin
modi_plus/assets/firmware/modules/display.bin
modi_plus/assets/firmware/modules/env.bin
modi_plus/assets/firmware/modules/imu.bin
modi_plus/assets/firmware/modules/joystick.bin
modi_plus/assets/firmware/modules/led.bin
modi_plus/assets/firmware/modules/motor.bin
modi_plus/assets/firmware/modules/network.bin
modi_plus/assets/firmware/modules/speaker.bin
modi_plus/assets/firmware/modules/tof.bin
modi_plus/module/__init__.py
modi_plus/module/module.py
modi_plus/module/input_module/__init__.py
modi_plus/module/input_module/button.py
modi_plus/module/input_module/dial.py
modi_plus/module/input_module/env.py
modi_plus/module/input_module/imu.py
modi_plus/module/input_module/joystick.py
modi_plus/module/input_module/tof.py
modi_plus/module/output_module/__init__.py
modi_plus/module/output_module/display.py
modi_plus/module/output_module/led.py
modi_plus/module/output_module/motor.py
modi_plus/module/output_module/speaker.py
modi_plus/module/setup_module/__init__.py
modi_plus/module/setup_module/battery.py
modi_plus/module/setup_module/network.py
modi_plus/task/__init__.py
modi_plus/task/connection_task.py
modi_plus/task/exe_task.py
modi_plus/task/serialport_task.py
modi_plus/task/ble_task/__init__.py
modi_plus/task/ble_task/ble_task_linux.py
modi_plus/task/ble_task/ble_task_mac.py
modi_plus/task/ble_task/ble_task_rpi.py
modi_plus/task/ble_task/ble_task_win.py
modi_plus/task/ble_task/change_interval.sh
modi_plus/util/__init__.py
modi_plus/util/connection_util.py
pymodi_plus-0.4.2.dist-info/licenses/LICENSE
pymodi_plus-0.4.2.dist-info/METADATA
pymodi_plus-0.4.2.dist-info/WHEEL
pymodi_plus-0.4.2.dist-info/top_level.txt
pymodi_plus-0.4.2.dist-info/RECORD
