Metadata-Version: 2.4
Name: pymodi-plus
Version: 0.4.2
Summary: Python API for controlling modular electronics, MODI+.
Home-page: https://github.com/LUXROBO/pymodi-plus
Author: LUXROBO
Author-email: module.dev@luxrobo.com
License: MIT
Keywords: python,modi,modi-plus,modi_plus,modi+
Classifier: Natural Language :: English
Classifier: Intended Audience :: Developers
Classifier: Intended Audience :: Education
Classifier: Intended Audience :: Information Technology
Classifier: Intended Audience :: Science/Research
Classifier: Programming Language :: Python :: 3
Classifier: License :: OSI Approved :: MIT License
Classifier: Operating System :: OS Independent
Requires-Python: >=3.7
License-File: LICENSE
Requires-Dist: pyserial==3.5
Requires-Dist: nest-asyncio==1.5.4
Requires-Dist: websocket-client==1.2.3
Requires-Dist: packaging>=21.3
Requires-Dist: bleak==0.13.0; sys_platform == "win32"
Requires-Dist: winusbcdc==1.4; sys_platform == "win32"
Requires-Dist: bleak==0.13.0; sys_platform == "darwin"
Requires-Dist: pexpect; sys_platform == "linux"
Provides-Extra: dev
Requires-Dist: flake8==4.0.1; extra == "dev"
Requires-Dist: black==24.3.0; extra == "dev"
Requires-Dist: tox==3.24.4; extra == "dev"
Requires-Dist: coverage==6.1.1; extra == "dev"
Dynamic: author
Dynamic: author-email
Dynamic: classifier
Dynamic: description
Dynamic: description-content-type
Dynamic: home-page
Dynamic: keywords
Dynamic: license
Dynamic: license-file
Dynamic: provides-extra
Dynamic: requires-dist
Dynamic: requires-python
Dynamic: summary
